{
  "game": {
    "appid": 1304930,
    "slug": "the-outlast-trials",
    "title": "The Outlast Trials",
    "version": "1.0",
    "lastPatchChecked": "2026-07-14",
    "estTotalHours": 30,
    "difficultyRating": 6,
    "minPlaythroughs": 1,
    "createdAt": "2026-07-15"
  },
  "roadmap": [
    {
      "step": 1,
      "title": "Build progress during the first 25 Trials",
      "description": "Finish Trials while collecting documents and items, using a RIG, running, crouching, sliding, hiding, and keeping night vision active. These counters overlap heavily with normal progression.",
      "achievementRefs": [
        "achievement_determined",
        "achievement_mechanophiliac",
        "achievement_big_saver",
        "achievement_hoarder",
        "achievement_marathonian",
        "achievement_hunchback",
        "achievement_drift_king",
        "achievement_clear_vision",
        "achievement_chicken_shit"
      ]
    },
    {
      "step": 2,
      "title": "Item, trap, damage, and throwable cleanup",
      "description": "Use the required consumables instead of carrying them to extraction; work locked containers, trapped doors, psychosis, damage, and all three throwable behaviors into the same runs.",
      "achievementRefs": [
        "achievement_sleight_of_hand",
        "achievement_trigger_happy",
        "achievement_anger_issues",
        "achievement_hypochondriac",
        "achievement_gotta_go_fast",
        "achievement_breathe_in",
        "achievement_power_surge",
        "achievement_boost_me_up",
        "achievement_bullseye",
        "achievement_major_league_player",
        "achievement_bamboozle",
        "achievement_high_as_a_kite",
        "achievement_hemophiliac"
      ]
    },
    {
      "step": 3,
      "title": "Co-op badge farming",
      "description": "Pair with a cooperative teammate to trade knockdowns and revives, interrupt enemy attacks with kicks, and complete two-person boost and door actions.",
      "achievementRefs": [
        "achievement_step_on_me_daddy",
        "achievement_no_time_to_sleep",
        "achievement_crowd_control",
        "achievement_together_we_are_stong"
      ]
    },
    {
      "step": 4,
      "title": "Ten distinct no-damage clears",
      "description": "Finish ten different Trials or MK-Challenges without losing health. Use familiar routes and defensive RIGs, and track unique credited missions rather than repeating one Trial.",
      "achievementRefs": [
        "achievement_cant_touch_this"
      ]
    }
  ],
  "achievements": [
    {
      "apiName": "achievement_big_saver",
      "displayName": "Big Saver",
      "description": "Collect 15 evidence documents.",
      "hidden": true,
      "globalPercent": 21.1,
      "flags": {
        "missable": false,
        "online": true,
        "grind": false,
        "glitched": false,
        "dlc": false
      },
      "difficulty": 2,
      "estTime": "3–10 h",
      "estMinutes": 360,
      "stage": 1,
      "confidence": "verified",
      "group": "general",
      "sortReason": "Roadmap stage 1; pursue alongside the other counters in this stage.",
      "prerequisites": [],
      "summary": "Collect 15 evidence documents across Trials.",
      "guide": {
        "kind": "standard",
        "context": "Evidence documents use randomized map spawns, so scan side rooms while completing the first 25 Trials.",
        "steps": [
          {
            "id": "achievement-big-saver-1",
            "text": "Search desks, shelves, and other side-room surfaces for evidence documents; pick up each document so it is added to the collection."
          },
          {
            "id": "achievement-big-saver-2",
            "text": "If documents are difficult to spot, equip the X-Ray RIG and activate it while searching. Collect 15 total to receive the badge."
          }
        ]
      }
    },
    {
      "apiName": "achievement_sleight_of_hand",
      "displayName": "Sleight of Hand",
      "description": "Unlock 100 containers.",
      "hidden": true,
      "globalPercent": 3.7,
      "flags": {
        "missable": false,
        "online": true,
        "grind": true,
        "glitched": false,
        "dlc": false
      },
      "difficulty": 3,
      "estTime": "4–12 h",
      "estMinutes": 480,
      "stage": 2,
      "confidence": "verified",
      "group": "general",
      "sortReason": "Roadmap stage 2; pursue alongside the other counters in this stage.",
      "prerequisites": [],
      "summary": "Open 100 locked containers with lockpicks.",
      "guide": {
        "kind": "standard",
        "context": "The counter is for unlocking containers, not merely opening unlocked boxes.",
        "steps": [
          {
            "id": "achievement-sleight-of-hand-1",
            "text": "Collect lockpicks during a Trial, approach a locked container, choose the Unlock prompt, and complete the lockpick timing check."
          },
          {
            "id": "achievement-sleight-of-hand-2",
            "text": "Key Master gives each lockpick two uses and first-try timing success. A Confidential Room master key also works repeatedly; the Lock Breaker AMP does not advance this badge. Reach 100 unlocked containers."
          }
        ]
      }
    },
    {
      "apiName": "achievement_mechanophiliac",
      "displayName": "Mechanophiliac",
      "description": "Use a RIG 100 times.",
      "hidden": true,
      "globalPercent": 18.9,
      "flags": {
        "missable": false,
        "online": true,
        "grind": true,
        "glitched": false,
        "dlc": false
      },
      "difficulty": 2,
      "estTime": "2–8 h",
      "estMinutes": 300,
      "stage": 1,
      "confidence": "verified",
      "group": "general",
      "sortReason": "Roadmap stage 1; pursue alongside the other counters in this stage.",
      "prerequisites": [],
      "summary": "Activate any RIG 100 times.",
      "guide": {
        "kind": "standard",
        "context": "Equip a RIG before entering Trials and spend its ability whenever it is ready.",
        "steps": [
          {
            "id": "achievement-mechanophiliac-1",
            "text": "At the loadout screen, equip any RIG; X-Ray is convenient because it can be activated without arranging an enemy encounter."
          },
          {
            "id": "achievement-mechanophiliac-2",
            "text": "During Trials, activate the equipped RIG whenever its cooldown has finished. Continue until the Badges screen reaches 100 uses."
          }
        ]
      }
    },
    {
      "apiName": "achievement_together_we_are_stong",
      "displayName": "Together We Are Strong",
      "description": "Perform 50 co-op moves.",
      "hidden": true,
      "globalPercent": 14.4,
      "flags": {
        "missable": false,
        "online": true,
        "grind": true,
        "glitched": false,
        "dlc": false
      },
      "difficulty": 3,
      "estTime": "2–8 h",
      "estMinutes": 300,
      "stage": 3,
      "confidence": "verified",
      "group": "co-op",
      "sortReason": "Roadmap stage 3; pursue alongside the other counters in this stage.",
      "prerequisites": [],
      "summary": "Complete 50 two-player co-op moves.",
      "guide": {
        "kind": "standard",
        "context": "Co-op moves include boosting a reagent onto a tall ledge and breaking a heavily boarded two-person door.",
        "steps": [
          {
            "id": "achievement-together-we-are-stong-1",
            "text": "In a co-op Trial, stand at a marked boost ledge or two-person boarded door and activate the on-screen co-op prompt."
          },
          {
            "id": "achievement-together-we-are-stong-2",
            "text": "Wait for the partner to join the action so the boost or door break finishes. Complete 50 such moves across Trials."
          }
        ]
      }
    },
    {
      "apiName": "achievement_crowd_control",
      "displayName": "Crowd Control",
      "description": "Help teammates by kicking 50 enemies.",
      "hidden": true,
      "globalPercent": 5.2,
      "flags": {
        "missable": false,
        "online": true,
        "grind": true,
        "glitched": false,
        "dlc": false
      },
      "difficulty": 4,
      "estTime": "3–10 h",
      "estMinutes": 360,
      "stage": 3,
      "confidence": "verified",
      "group": "co-op",
      "sortReason": "Roadmap stage 3; pursue alongside the other counters in this stage.",
      "prerequisites": [],
      "summary": "Kick enemies off teammates 50 times.",
      "guide": {
        "kind": "standard",
        "context": "Kick opportunities occur when an enemy attacks or executes another reagent, including attacks from hiding spots.",
        "steps": [
          {
            "id": "achievement-crowd-control-1",
            "text": "Stay near a co-op partner. When an enemy grabs, attacks, or begins executing that partner, approach the attacker and use the on-screen Kick prompt before the sequence ends."
          },
          {
            "id": "achievement-crowd-control-2",
            "text": "Successfully interrupt 50 enemy attacks this way; deliberate farming is easiest with a partner and a controlled low-threat enemy."
          }
        ]
      }
    },
    {
      "apiName": "achievement_hypochondriac",
      "displayName": "Hypochondriac",
      "description": "Consume 200 medicines.",
      "hidden": true,
      "globalPercent": 3.8,
      "flags": {
        "missable": false,
        "online": true,
        "grind": true,
        "glitched": false,
        "dlc": false
      },
      "difficulty": 3,
      "estTime": "8–20 h",
      "estMinutes": 720,
      "stage": 2,
      "confidence": "verified",
      "group": "general",
      "sortReason": "Roadmap stage 2; pursue alongside the other counters in this stage.",
      "prerequisites": [],
      "summary": "Consume 200 medicine items.",
      "guide": {
        "kind": "standard",
        "context": "Small and large medicines appear on surfaces, in wall-mounted first-aid boxes, on dead reagents, and in Confidential Rooms.",
        "steps": [
          {
            "id": "achievement-hypochondriac-1",
            "text": "After losing health, pick up a small or large medicine and use its Consume input; simply collecting it does not satisfy the badge."
          },
          {
            "id": "achievement-hypochondriac-2",
            "text": "Favor medicine items over the Heal RIG while pursuing this counter, and repeat until 200 medicines have been consumed."
          }
        ]
      }
    },
    {
      "apiName": "achievement_no_time_to_sleep",
      "displayName": "Sawbones",
      "description": "Revive or help up a friend 50 times.",
      "hidden": true,
      "globalPercent": 5.9,
      "flags": {
        "missable": false,
        "online": true,
        "grind": true,
        "glitched": false,
        "dlc": false
      },
      "difficulty": 4,
      "estTime": "2–8 h",
      "estMinutes": 300,
      "stage": 3,
      "confidence": "verified",
      "group": "co-op",
      "sortReason": "Roadmap stage 3; pursue alongside the other counters in this stage.",
      "prerequisites": [],
      "summary": "Revive or help up teammates 50 times.",
      "guide": {
        "kind": "standard",
        "context": "Both helping up a downed teammate and reviving with a syringe advance the same counter.",
        "steps": [
          {
            "id": "achievement-no-time-to-sleep-1",
            "text": "When a teammate is downed, move beside them and hold the on-screen Help Up prompt until they stand; if they are dead, collect a syringe and use the Revive prompt instead."
          },
          {
            "id": "achievement-no-time-to-sleep-2",
            "text": "Repeat either recovery action 50 times. The Medic prescription shortens revives but is optional."
          }
        ]
      }
    },
    {
      "apiName": "achievement_gotta_go_fast",
      "displayName": "Speed Freak",
      "description": "Use 50 adrenalines.",
      "hidden": true,
      "globalPercent": 6.2,
      "flags": {
        "missable": false,
        "online": true,
        "grind": true,
        "glitched": false,
        "dlc": false
      },
      "difficulty": 2,
      "estTime": "4–12 h",
      "estMinutes": 480,
      "stage": 2,
      "confidence": "verified",
      "group": "general",
      "sortReason": "Roadmap stage 2; pursue alongside the other counters in this stage.",
      "prerequisites": [],
      "summary": "Consume 50 adrenaline items.",
      "guide": {
        "kind": "standard",
        "context": "Adrenaline appears in first-aid boxes, on open surfaces, and on dead reagents.",
        "steps": [
          {
            "id": "achievement-gotta-go-fast-1",
            "text": "Pick up an adrenaline, select it in the inventory, and use it to gain the temporary speed and unlimited-stamina effect."
          },
          {
            "id": "achievement-gotta-go-fast-2",
            "text": "Consume each one rather than carrying it to the exit; repeat until 50 uses register."
          }
        ]
      }
    },
    {
      "apiName": "achievement_breathe_in",
      "displayName": "Breathe In",
      "description": "Use 100 antidotes.",
      "hidden": true,
      "globalPercent": 4.1,
      "flags": {
        "missable": false,
        "online": true,
        "grind": true,
        "glitched": false,
        "dlc": false
      },
      "difficulty": 3,
      "estTime": "8–20 h",
      "estMinutes": 720,
      "stage": 2,
      "confidence": "verified",
      "group": "general",
      "sortReason": "Roadmap stage 2; pursue alongside the other counters in this stage.",
      "prerequisites": [],
      "summary": "Consume 100 antidotes.",
      "guide": {
        "kind": "standard",
        "context": "Antidotes can be found on surfaces, on dead reagents, and inside first-aid boxes; full psychosis also highlights a nearby one.",
        "steps": [
          {
            "id": "achievement-breathe-in-1",
            "text": "Collect an antidote, select it in the inventory, and use it when psychosis has reduced sanity."
          },
          {
            "id": "achievement-breathe-in-2",
            "text": "Continue consuming antidotes during Trials until the badge counter reaches 100."
          }
        ]
      }
    },
    {
      "apiName": "achievement_power_surge",
      "displayName": "Power Surge",
      "description": "Use 100 batteries.",
      "hidden": true,
      "globalPercent": 15.6,
      "flags": {
        "missable": false,
        "online": true,
        "grind": true,
        "glitched": false,
        "dlc": false
      },
      "difficulty": 2,
      "estTime": "5–15 h",
      "estMinutes": 600,
      "stage": 2,
      "confidence": "verified",
      "group": "general",
      "sortReason": "Roadmap stage 2; pursue alongside the other counters in this stage.",
      "prerequisites": [],
      "summary": "Use 100 battery items.",
      "guide": {
        "kind": "standard",
        "context": "Small and large batteries restore the night-vision goggles and commonly appear in technical boxes; Confidential Rooms can contain large batteries.",
        "steps": [
          {
            "id": "achievement-power-surge-1",
            "text": "Run the night-vision charge below full, select a battery, and use it to refill the goggles; merely picking up a battery is insufficient."
          },
          {
            "id": "achievement-power-surge-2",
            "text": "Keep night vision active to create recharge opportunities and use 100 batteries in total."
          }
        ]
      }
    },
    {
      "apiName": "achievement_bullseye",
      "displayName": "Bullseye",
      "description": "Headshot 50 enemies.",
      "hidden": true,
      "globalPercent": 18.6,
      "flags": {
        "missable": false,
        "online": true,
        "grind": true,
        "glitched": false,
        "dlc": false
      },
      "difficulty": 3,
      "estTime": "2–8 h",
      "estMinutes": 300,
      "stage": 2,
      "confidence": "verified",
      "group": "general",
      "sortReason": "Roadmap stage 2; pursue alongside the other counters in this stage.",
      "prerequisites": [],
      "summary": "Hit enemies in the head with 50 throwables.",
      "guide": {
        "kind": "standard",
        "context": "Bricks and bottles are the standard throwables; stationary, unaware Ex-Pops are the easiest targets.",
        "steps": [
          {
            "id": "achievement-bullseye-1",
            "text": "Equip a brick or bottle, aim at an enemy's head, and throw it for a direct head impact."
          },
          {
            "id": "achievement-bullseye-2",
            "text": "Repeat direct headshots on 50 enemies. The Recycle AMP can convert used medicine bottles into extra throwables."
          }
        ]
      }
    },
    {
      "apiName": "achievement_major_league_player",
      "displayName": "Major League Player",
      "description": "Hit 100 enemies with throwables.",
      "hidden": true,
      "globalPercent": 13.4,
      "flags": {
        "missable": false,
        "online": true,
        "grind": true,
        "glitched": false,
        "dlc": false
      },
      "difficulty": 2,
      "estTime": "3–10 h",
      "estMinutes": 360,
      "stage": 2,
      "confidence": "verified",
      "group": "general",
      "sortReason": "Roadmap stage 2; pursue alongside the other counters in this stage.",
      "prerequisites": [],
      "summary": "Land 100 direct throwable hits on enemies.",
      "guide": {
        "kind": "standard",
        "context": "This badge counts direct impacts from items such as bricks and bottles.",
        "steps": [
          {
            "id": "achievement-major-league-player-1",
            "text": "Pick up a brick or bottle, aim at an enemy's body, and throw it so the item directly connects."
          },
          {
            "id": "achievement-major-league-player-2",
            "text": "Collect replacement throwables after each impact and continue until 100 enemy hits have registered; Strong Arm increases the effect but is not required."
          }
        ]
      }
    },
    {
      "apiName": "achievement_bamboozle",
      "displayName": "Bamboozler",
      "description": "Distract 50 enemies with throwables.",
      "hidden": true,
      "globalPercent": 10.8,
      "flags": {
        "missable": false,
        "online": true,
        "grind": true,
        "glitched": false,
        "dlc": false
      },
      "difficulty": 3,
      "estTime": "2–8 h",
      "estMinutes": 300,
      "stage": 2,
      "confidence": "verified",
      "group": "general",
      "sortReason": "Roadmap stage 2; pursue alongside the other counters in this stage.",
      "prerequisites": [],
      "summary": "Distract enemies 50 times with thrown objects.",
      "guide": {
        "kind": "standard",
        "context": "A distraction is created by noise near an enemy; a direct hit belongs to the separate throwable-hit counters.",
        "steps": [
          {
            "id": "achievement-bamboozle-1",
            "text": "Throw a bottle or brick onto a floor or wall close enough for an enemy to hear, deliberately missing the enemy's body."
          },
          {
            "id": "achievement-bamboozle-2",
            "text": "Wait for the enemy to react and investigate the sound, then repeat until 50 distractions have registered; bottles create the louder distraction."
          }
        ]
      }
    },
    {
      "apiName": "achievement_chicken_shit",
      "displayName": "Chicken in a Pot",
      "description": "Use 100 hiding spots.",
      "hidden": true,
      "globalPercent": 17.5,
      "flags": {
        "missable": false,
        "online": true,
        "grind": true,
        "glitched": false,
        "dlc": false
      },
      "difficulty": 2,
      "estTime": "1–4 h",
      "estMinutes": 180,
      "stage": 1,
      "confidence": "verified",
      "group": "general",
      "sortReason": "Roadmap stage 1; pursue alongside the other counters in this stage.",
      "prerequisites": [],
      "summary": "Enter hiding spots 100 times.",
      "guide": {
        "kind": "standard",
        "context": "Lockers, barrels, spaces under desks, and map-specific containers count as hiding spots.",
        "steps": [
          {
            "id": "achievement-chicken-shit-1",
            "text": "Approach a valid hiding place and use its on-screen Hide prompt to enter it fully."
          },
          {
            "id": "achievement-chicken-shit-2",
            "text": "Leave the spot and repeat with hiding places encountered during Trials until 100 entries have registered; Hide and Heal or Hide and Breathe adds utility while farming."
          }
        ]
      }
    },
    {
      "apiName": "achievement_trigger_happy",
      "displayName": "Trigger Happy",
      "description": "Disarm 50 door traps.",
      "hidden": true,
      "globalPercent": 8.1,
      "flags": {
        "missable": false,
        "online": true,
        "grind": true,
        "glitched": false,
        "dlc": false
      },
      "difficulty": 3,
      "estTime": "3–10 h",
      "estMinutes": 360,
      "stage": 2,
      "confidence": "verified",
      "group": "general",
      "sortReason": "Roadmap stage 2; pursue alongside the other counters in this stage.",
      "prerequisites": [],
      "summary": "Disarm 50 trapped doors.",
      "guide": {
        "kind": "standard",
        "context": "A trapped door can be disarmed only from the side with the removable battery.",
        "steps": [
          {
            "id": "achievement-trigger-happy-1",
            "text": "Inspect doors for a trap before passing through. If the battery is on the far side, hold the Open input to ease the door open and slip around without triggering it."
          },
          {
            "id": "achievement-trigger-happy-2",
            "text": "On the battery side, use the Disarm prompt and remove the battery. Repeat on 50 trapped doors."
          }
        ]
      }
    },
    {
      "apiName": "achievement_anger_issues",
      "displayName": "Anger Issues",
      "description": "Break down 50 locked doors.",
      "hidden": true,
      "globalPercent": 9.1,
      "flags": {
        "missable": false,
        "online": true,
        "grind": true,
        "glitched": false,
        "dlc": false
      },
      "difficulty": 2,
      "estTime": "2–8 h",
      "estMinutes": 300,
      "stage": 2,
      "confidence": "verified",
      "group": "general",
      "sortReason": "Roadmap stage 2; pursue alongside the other counters in this stage.",
      "prerequisites": [],
      "summary": "Bash open 50 locked doors.",
      "guide": {
        "kind": "standard",
        "context": "Only doors that begin locked count toward this badge.",
        "steps": [
          {
            "id": "achievement-anger-issues-1",
            "text": "When a door refuses the normal Open input, use the Bash input repeatedly until the lock breaks and the door opens."
          },
          {
            "id": "achievement-anger-issues-2",
            "text": "The Doors Basher prescription reduces the job to two hits. Break 50 locked doors in this way."
          }
        ]
      }
    },
    {
      "apiName": "achievement_determined",
      "displayName": "Glutton for Therapy",
      "description": "Complete 25 Trials.",
      "hidden": true,
      "globalPercent": 18.4,
      "flags": {
        "missable": false,
        "online": true,
        "grind": true,
        "glitched": false,
        "dlc": false
      },
      "difficulty": 3,
      "estTime": "20–25 h",
      "estMinutes": 1200,
      "stage": 1,
      "confidence": "verified",
      "group": "general",
      "sortReason": "Roadmap stage 1; pursue alongside the other counters in this stage.",
      "prerequisites": [],
      "summary": "Complete 25 Trials.",
      "guide": {
        "kind": "standard",
        "context": "This is the backbone of the completion route; every finished Trial counts toward 25.",
        "steps": [
          {
            "id": "achievement-determined-1",
            "text": "Choose any available Trial or MK-Challenge at the Sleep Room terminal, finish its objectives, and reach the shuttle exit."
          },
          {
            "id": "achievement-determined-2",
            "text": "Repeat until the Badges screen records 25 completed Trials and awards Glutton for Therapy."
          }
        ]
      }
    },
    {
      "apiName": "achievement_boost_me_up",
      "displayName": "Toastmaster",
      "description": "Use 50 RIG Rechargers.",
      "hidden": true,
      "globalPercent": 4.5,
      "flags": {
        "missable": false,
        "online": true,
        "grind": true,
        "glitched": false,
        "dlc": false
      },
      "difficulty": 3,
      "estTime": "8–20 h",
      "estMinutes": 720,
      "stage": 2,
      "confidence": "verified",
      "group": "general",
      "sortReason": "Roadmap stage 2; pursue alongside the other counters in this stage.",
      "prerequisites": [],
      "summary": "Consume 50 RIG Rechargers.",
      "guide": {
        "kind": "standard",
        "context": "RIG Rechargers are uncommon technical-box and Confidential Room items.",
        "steps": [
          {
            "id": "achievement-boost-me-up-1",
            "text": "Activate the equipped RIG so that it enters cooldown, then collect and use a RIG Recharger to make the ability ready immediately."
          },
          {
            "id": "achievement-boost-me-up-2",
            "text": "Do not save rechargers until extraction; use 50 while a RIG is cooling down to complete the badge."
          }
        ]
      }
    },
    {
      "apiName": "achievement_clear_vision",
      "displayName": "Tapetum Lucidum",
      "description": "Spend 36,000 seconds in night vision.",
      "hidden": true,
      "globalPercent": 8.2,
      "flags": {
        "missable": false,
        "online": true,
        "grind": true,
        "glitched": false,
        "dlc": false
      },
      "difficulty": 3,
      "estTime": "10–20 h",
      "estMinutes": 720,
      "stage": 1,
      "confidence": "verified",
      "group": "general",
      "sortReason": "Roadmap stage 1; pursue alongside the other counters in this stage.",
      "prerequisites": [],
      "summary": "Use night vision for a cumulative 10 hours.",
      "guide": {
        "kind": "standard",
        "context": "The badge requires 36,000 seconds—10 hours—with night vision switched on.",
        "steps": [
          {
            "id": "achievement-clear-vision-1",
            "text": "Turn on the night-vision goggles during dark routes and keep them active while battery charge remains."
          },
          {
            "id": "achievement-clear-vision-2",
            "text": "Use batteries to restore charge; Night Crawler, Battery Charger, and Battery Extension can stretch each charge. Accumulate 36,000 seconds with night vision active."
          }
        ]
      }
    },
    {
      "apiName": "achievement_high_as_a_kite",
      "displayName": "Vision Quest",
      "description": "Spend 600 seconds in full psychosis.",
      "hidden": true,
      "globalPercent": 9.5,
      "flags": {
        "missable": false,
        "online": true,
        "grind": true,
        "glitched": false,
        "dlc": false
      },
      "difficulty": 4,
      "estTime": "1–4 h",
      "estMinutes": 180,
      "stage": 2,
      "confidence": "verified",
      "group": "general",
      "sortReason": "Roadmap stage 2; pursue alongside the other counters in this stage.",
      "prerequisites": [],
      "summary": "Survive 10 cumulative minutes in full psychosis.",
      "guide": {
        "kind": "standard",
        "context": "Door, container, and mine traps or the Pusher can reduce sanity to full psychosis; using an antidote ends the state.",
        "steps": [
          {
            "id": "achievement-high-as-a-kite-1",
            "text": "On a manageable Trial, allow a psychosis source to empty the sanity meter and trigger full psychosis."
          },
          {
            "id": "achievement-high-as-a-kite-2",
            "text": "Avoid the Skinner Man and postpone the antidote while safe. Accumulate 600 seconds in full psychosis across attempts, then use an antidote when necessary to survive."
          }
        ]
      }
    },
    {
      "apiName": "achievement_step_on_me_daddy",
      "displayName": "Get Down",
      "description": "Be knocked down 50 times.",
      "hidden": true,
      "globalPercent": 10.0,
      "flags": {
        "missable": false,
        "online": true,
        "grind": true,
        "glitched": false,
        "dlc": false
      },
      "difficulty": 4,
      "estTime": "2–6 h",
      "estMinutes": 240,
      "stage": 3,
      "confidence": "verified",
      "group": "co-op",
      "sortReason": "Roadmap stage 3; pursue alongside the other counters in this stage.",
      "prerequisites": [],
      "summary": "Enter the downed state 50 times.",
      "guide": {
        "kind": "standard",
        "context": "A teammate is needed to restore you repeatedly without ending the Trial.",
        "steps": [
          {
            "id": "achievement-step-on-me-daddy-1",
            "text": "Enter a co-op Trial with a partner, let an enemy remove your remaining health, and wait until your reagent reaches the downed state."
          },
          {
            "id": "achievement-step-on-me-daddy-2",
            "text": "Have the partner use Help Up or a syringe after the enemy moves away. Repeat the down-and-recovery cycle until 50 knockdowns register."
          }
        ]
      }
    },
    {
      "apiName": "achievement_hemophiliac",
      "displayName": "Hemophiliac",
      "description": "Lose 10,000 health points.",
      "hidden": true,
      "globalPercent": 11.8,
      "flags": {
        "missable": false,
        "online": true,
        "grind": true,
        "glitched": false,
        "dlc": false
      },
      "difficulty": 3,
      "estTime": "8–20 h",
      "estMinutes": 720,
      "stage": 2,
      "confidence": "verified",
      "group": "general",
      "sortReason": "Roadmap stage 2; pursue alongside the other counters in this stage.",
      "prerequisites": [],
      "summary": "Lose a cumulative 10,000 health points.",
      "guide": {
        "kind": "standard",
        "context": "Healing permits more enemy damage to be accumulated safely during one Trial.",
        "steps": [
          {
            "id": "achievement-hemophiliac-1",
            "text": "Carry medicine or equip the Heal RIG, then allow a low-threat enemy to damage you without letting the Trial fail."
          },
          {
            "id": "achievement-hemophiliac-2",
            "text": "Retreat, restore health, and repeat. Accumulate 10,000 health points lost across Trials to receive the badge."
          }
        ]
      }
    },
    {
      "apiName": "achievement_hoarder",
      "displayName": "Hoarder",
      "description": "Collect 1,000 items.",
      "hidden": true,
      "globalPercent": 8.1,
      "flags": {
        "missable": false,
        "online": true,
        "grind": true,
        "glitched": false,
        "dlc": false
      },
      "difficulty": 2,
      "estTime": "10–20 h",
      "estMinutes": 900,
      "stage": 1,
      "confidence": "verified",
      "group": "general",
      "sortReason": "Roadmap stage 1; pursue alongside the other counters in this stage.",
      "prerequisites": [],
      "summary": "Pick up 1,000 items.",
      "guide": {
        "kind": "standard",
        "context": "Nearly every useful object found inside a Trial advances this cumulative badge.",
        "steps": [
          {
            "id": "achievement-hoarder-1",
            "text": "Pick up medicine, batteries, throwables, lockpicks, and other portable Trial items whenever inventory space permits."
          },
          {
            "id": "achievement-hoarder-2",
            "text": "Use, drop, or hand items to teammates to free slots, then keep collecting until the badge counter reaches 1,000."
          }
        ]
      }
    },
    {
      "apiName": "achievement_drift_king",
      "displayName": "Slip and Slider",
      "description": "Spend 120 seconds sliding.",
      "hidden": true,
      "globalPercent": 14.0,
      "flags": {
        "missable": false,
        "online": true,
        "grind": true,
        "glitched": false,
        "dlc": false
      },
      "difficulty": 2,
      "estTime": "20–60 min",
      "estMinutes": 45,
      "stage": 1,
      "confidence": "verified",
      "group": "general",
      "sortReason": "Roadmap stage 1; pursue alongside the other counters in this stage.",
      "prerequisites": [],
      "summary": "Accumulate two minutes of sliding.",
      "guide": {
        "kind": "standard",
        "context": "Unlock the Tier 1 Slide prescription from Emily Barlow at the Pharmacy in the Sleep Room; prescriptions become active when purchased and are not equipped or toggled.",
        "steps": [
          {
            "id": "achievement-drift-king-1",
            "text": "In the Sleep Room, visit Emily Barlow at the Pharmacy and purchase the Tier 1 Slide prescription. Enter a Trial, sprint, and press Crouch to begin a slide."
          },
          {
            "id": "achievement-drift-king-2",
            "text": "Work a slide into safe running routes until the cumulative sliding timer reaches 120 seconds."
          }
        ]
      }
    },
    {
      "apiName": "achievement_marathonian",
      "displayName": "Marathoner",
      "description": "Spend 3,600 seconds running.",
      "hidden": true,
      "globalPercent": 32.7,
      "flags": {
        "missable": false,
        "online": true,
        "grind": true,
        "glitched": false,
        "dlc": false
      },
      "difficulty": 2,
      "estTime": "1–4 h",
      "estMinutes": 180,
      "stage": 1,
      "confidence": "verified",
      "group": "general",
      "sortReason": "Roadmap stage 1; pursue alongside the other counters in this stage.",
      "prerequisites": [],
      "summary": "Accumulate 60 minutes of running.",
      "guide": {
        "kind": "standard",
        "context": "The required 3,600 seconds equal one hour and accrue across Trials.",
        "steps": [
          {
            "id": "achievement-marathonian-1",
            "text": "Hold the Run input while moving through safe routes and between objectives; the Endurance prescription reduces the stamina cost."
          },
          {
            "id": "achievement-marathonian-2",
            "text": "Accumulate 3,600 seconds of actual running across sessions to complete the badge."
          }
        ]
      }
    },
    {
      "apiName": "achievement_hunchback",
      "displayName": "Hunchback",
      "description": "Spend 3,600 seconds crouched.",
      "hidden": true,
      "globalPercent": 28.6,
      "flags": {
        "missable": false,
        "online": true,
        "grind": true,
        "glitched": false,
        "dlc": false
      },
      "difficulty": 2,
      "estTime": "1–5 h",
      "estMinutes": 240,
      "stage": 1,
      "confidence": "verified",
      "group": "general",
      "sortReason": "Roadmap stage 1; pursue alongside the other counters in this stage.",
      "prerequisites": [],
      "summary": "Accumulate 60 minutes while crouched.",
      "guide": {
        "kind": "standard",
        "context": "Crouched movement and stationary crouching both contribute to the 3,600-second total.",
        "steps": [
          {
            "id": "achievement-hunchback-1",
            "text": "Use the Crouch input while searching rooms and moving past enemies; Night Crawler makes crouch-walking faster and improves night-vision battery efficiency."
          },
          {
            "id": "achievement-hunchback-2",
            "text": "Remain crouched for a cumulative 3,600 seconds across Trials to earn the badge."
          }
        ]
      }
    },
    {
      "apiName": "achievement_cant_touch_this",
      "displayName": "Can't Touch This",
      "description": "Complete 10 different Trials or MK-Challenges without taking damage.",
      "hidden": true,
      "globalPercent": 4.3,
      "flags": {
        "missable": false,
        "online": true,
        "grind": true,
        "glitched": false,
        "dlc": false
      },
      "difficulty": 7,
      "estTime": "5–15 h",
      "estMinutes": 600,
      "stage": 4,
      "confidence": "verified",
      "group": "general",
      "sortReason": "Roadmap stage 4; pursue alongside the other counters in this stage.",
      "prerequisites": [],
      "summary": "Finish 10 distinct Trials or MK-Challenges without damage.",
      "guide": {
        "kind": "standard",
        "context": "The current badge requirement is ten different completed Trials or MK-Challenges; repeating one mission does not satisfy the distinct-completion requirement.",
        "steps": [
          {
            "id": "achievement-cant-touch-this-1",
            "text": "Select a Trial or MK-Challenge not yet credited for this badge. A fully upgraded Stun or Blind RIG and a familiar low-threat route reduce risk."
          },
          {
            "id": "achievement-cant-touch-this-2",
            "text": "Complete every objective and reach extraction without taking health damage from enemies, traps, or the environment."
          },
          {
            "id": "achievement-cant-touch-this-3",
            "text": "Repeat the no-damage clear on nine other distinct Trials or MK-Challenges until the badge awards after the tenth unique clear."
          }
        ]
      }
    }
  ],
  "completionOrder": [
    "achievement_determined",
    "achievement_mechanophiliac",
    "achievement_big_saver",
    "achievement_hoarder",
    "achievement_marathonian",
    "achievement_hunchback",
    "achievement_drift_king",
    "achievement_clear_vision",
    "achievement_chicken_shit",
    "achievement_sleight_of_hand",
    "achievement_trigger_happy",
    "achievement_anger_issues",
    "achievement_hypochondriac",
    "achievement_gotta_go_fast",
    "achievement_breathe_in",
    "achievement_power_surge",
    "achievement_boost_me_up",
    "achievement_bullseye",
    "achievement_major_league_player",
    "achievement_bamboozle",
    "achievement_high_as_a_kite",
    "achievement_hemophiliac",
    "achievement_step_on_me_daddy",
    "achievement_no_time_to_sleep",
    "achievement_crowd_control",
    "achievement_together_we_are_stong",
    "achievement_cant_touch_this"
  ]
}
