{
  "game": {
    "appid": 3751950,
    "slug": "assassin-s-creed-black-flag-resynced",
    "title": "Assassin's Creed Black Flag Resynced",
    "version": "1.0",
    "lastPatchChecked": "2026-07-14",
    "estTotalHours": 45,
    "difficultyRating": 4,
    "minPlaythroughs": 1,
    "createdAt": "2026-07-15"
  },
  "roadmap": [
    {
      "step": 1,
      "title": "Story start and opportunistic combat",
      "description": "Play through Sequence 4 on Easy, taking the automatic story unlocks and simple combat, food, diving and exploration achievements as opportunities appear. Use a manual save before Sequence 2 Memory 6 if you want the guaranteed rogue wave for Unsinkable.",
      "achievementRefs": [
        "ACObsidian_Ach_8",
        "ACObsidian_Ach_12",
        "ACObsidian_Ach_13",
        "ACObsidian_Ach_15",
        "ACObsidian_Ach_16",
        "ACObsidian_Ach_18",
        "ACObsidian_Ach_20",
        "ACObsidian_Ach_23",
        "ACObsidian_Ach_24",
        "ACObsidian_Ach_25",
        "ACObsidian_Ach_29",
        "ACObsidian_Ach_32",
        "ACObsidian_Ach_33",
        "ACObsidian_Ach_38",
        "ACObsidian_Ach_40",
        "ACObsidian_Ach_43",
        "ACObsidian_Ach_48",
        "ACObsidian_Ach_49"
      ]
    },
    {
      "step": 2,
      "title": "Great Inagua, officers and fleet",
      "description": "After Sequence 4 Memory 1, restore Great Inagua, begin every officer/Templar quest, and keep five Brigs running piracy missions for Dilettante art rewards. Build money and materials through boarding rather than grinding them at the end.",
      "achievementRefs": [
        "ACObsidian_Ach_3",
        "ACObsidian_Ach_5",
        "ACObsidian_Ach_6",
        "ACObsidian_Ach_7",
        "ACObsidian_Ach_9",
        "ACObsidian_Ach_10",
        "ACObsidian_Ach_17",
        "ACObsidian_Ach_19",
        "ACObsidian_Ach_21",
        "ACObsidian_Ach_22",
        "ACObsidian_Ach_30",
        "ACObsidian_Ach_31",
        "ACObsidian_Ach_34",
        "ACObsidian_Ach_35",
        "ACObsidian_Ach_37",
        "ACObsidian_Ach_39",
        "ACObsidian_Ach_41"
      ]
    },
    {
      "step": 3,
      "title": "Diving and world completion",
      "description": "After Sequence 6 Memory 1 unlocks the diving bell, clear all seven shipwrecks and their 68 chests, visit every location, capture forts, collect portraits and interact with all eight friendly animals as the story opens the map.",
      "achievementRefs": [
        "ACObsidian_Ach_2",
        "ACObsidian_Ach_11",
        "ACObsidian_Ach_14",
        "ACObsidian_Ach_44",
        "ACObsidian_Ach_46",
        "ACObsidian_Ach_47"
      ]
    },
    {
      "step": 4,
      "title": "Finish the story and endgame naval work",
      "description": "Finish the remaining sequences, recruit the final officers, collect the 12 Ultimate Plans and fully upgrade the Jackdaw before challenging the five legendary encounters.",
      "achievementRefs": [
        "ACObsidian_Ach_26",
        "ACObsidian_Ach_27",
        "ACObsidian_Ach_28",
        "ACObsidian_Ach_36",
        "ACObsidian_Ach_42",
        "ACObsidian_Ach_45"
      ]
    },
    {
      "step": 5,
      "title": "Manor, RNG and final cleanup",
      "description": "Fill every manor display, finish cumulative counters, then farm the rare Burning Ship chair with a manual-save/fast-travel loop. Free roam remains available, so nothing is permanently lost.",
      "achievementRefs": [
        "ACObsidian_Ach_1",
        "ACObsidian_Ach_4"
      ]
    }
  ],
  "achievements": [
    {
      "apiName": "ACObsidian_Ach_1",
      "displayName": "Last To Leave",
      "description": "Take a seat on the deck of a rare Burning Ship event.",
      "hidden": true,
      "globalPercent": 3.3,
      "flags": {
        "missable": false,
        "online": false,
        "grind": true,
        "glitched": false,
        "dlc": false
      },
      "difficulty": 5,
      "estTime": "30–90 min RNG farm",
      "estMinutes": 60,
      "stage": 5,
      "confidence": "verified",
      "summary": "Sit in the @item{chair} on the rare chair variant of a @mechanic{Burning Ship} event.",
      "guide": {
        "kind": "standard",
        "context": "Burning Ships are timed white world events; only a small fraction spawn with the required chair on deck. Wait until @loc{Black Trench} is available after Sequence 6 Memory 1.",
        "steps": [
          {
            "id": "save",
            "text": "Make a manual save inside the @loc{Great Inagua manor} at 826,444, then fast-travel to @loc{Black Trench} at 184,425."
          },
          {
            "id": "scan",
            "text": "Use the spyglass immediately and look for a white timed Burning Ship icon. If none appears—or its deck has no chair—reload the manual save and repeat the fast travel."
          },
          {
            "id": "sit",
            "text": "When the chair variant appears, sail over before the five-minute event expires, board the already-burning wreck and use the interaction prompt to sit in the chair at mid-deck."
          }
        ]
      }
    },
    {
      "apiName": "ACObsidian_Ach_2",
      "displayName": "King of the Castle",
      "description": "Capture all forts",
      "hidden": false,
      "globalPercent": 4.2,
      "flags": {
        "missable": false,
        "online": false,
        "grind": false,
        "glitched": false,
        "dlc": false
      },
      "difficulty": 4,
      "estTime": "3–4 hours",
      "estMinutes": 210,
      "stage": 3,
      "confidence": "verified",
      "summary": "Capture all 11 @mechanic{forts} across the Caribbean.",
      "guide": {
        "kind": "standard",
        "context": "Forts are the red tower icons visible from sea. All remain available in free roam.",
        "steps": [
          {
            "id": "approach",
            "text": "Approach each fort to reveal its defenses, then use the Jackdaw to destroy every marked tower."
          },
          {
            "id": "storm",
            "text": "Dock at the damaged fort, storm the walls, kill the marked officers and open the command-room gate."
          },
          {
            "id": "finish",
            "text": "Repeat for all 11 forts; the achievement unlocks when the last fort changes to friendly control."
          }
        ]
      }
    },
    {
      "apiName": "ACObsidian_Ach_3",
      "displayName": "The Memory of My Enemy",
      "description": "Display all character portraits in the Great Inagua manor",
      "hidden": false,
      "globalPercent": 0.3,
      "flags": {
        "missable": false,
        "online": false,
        "grind": false,
        "glitched": false,
        "dlc": false
      },
      "difficulty": 2,
      "estTime": "2 hours",
      "estMinutes": 120,
      "stage": 2,
      "confidence": "verified",
      "summary": "Collect all 11 @item{character portraits} and hang them in the @loc{Great Inagua manor}.",
      "guide": {
        "kind": "collectible",
        "context": "Do this after the story: portraits only appear when their story gates are met and are revealed on the map only at close range. After collecting all 11, hang them in the manor's 11 frames (3 near the fleet room, 1 bedroom, 1 stairwell and 6 treasure cellar).",
        "collectibles": [
          {
            "id": "portrait-1",
            "index": 1,
            "name": "Julien Du Casse",
            "location": "Great Inagua manor weapon room, 827,443",
            "method": "Pick it up inside the manor.",
            "missable": false
          },
          {
            "id": "portrait-2",
            "index": 2,
            "name": "Laureano de Torres",
            "location": "Havana castle north-west tower, 224,595",
            "method": "Climb down from the wooden board above the open window and enter the tower.",
            "missable": false
          },
          {
            "id": "portrait-3",
            "index": 3,
            "name": "El Tiburón",
            "location": "Havana north castle, 204,608",
            "method": "Use the exterior corner scaffold to reach the open window; the Codex incorrectly labels this one Castillo.",
            "missable": false
          },
          {
            "id": "portrait-4",
            "index": 4,
            "name": "Commodore Chamberlaine",
            "location": "Nassau west manor, 589,757",
            "method": "Climb through an upper-floor window and collect it inside.",
            "missable": false
          },
          {
            "id": "portrait-5",
            "index": 5,
            "name": "Woodes Rogers",
            "location": "Kingston central manor, 618,171",
            "method": "Collect it after reaching Sequence 12 Memory 1.",
            "missable": false
          },
          {
            "id": "portrait-6",
            "index": 6,
            "name": "Laurens Prins",
            "location": "Kingston west plantation manor, 594,174",
            "method": "Enter after completing Sequence 5 Memory 3.",
            "missable": false
          },
          {
            "id": "portrait-7",
            "index": 7,
            "name": "Ben Hornigold",
            "location": "Santanillas north-east shipwreck, 191,223",
            "method": "Search the wreck on the island's north-east shore.",
            "missable": false
          },
          {
            "id": "portrait-8",
            "index": 8,
            "name": "Bartholomew Roberts",
            "location": "Príncipe north-east tent, 113,20",
            "method": "After Sequence 9 Memory 2, return via the white P icon at 939,415 and search the camp tent.",
            "missable": false
          },
          {
            "id": "portrait-9",
            "index": 9,
            "name": "Blackbeard",
            "location": "Blackbeard's Treasure side quest, Anotto Bay 590,245",
            "method": "After Sequence 8 Memory 1, finish the cave treasure route, then open the updated quest chest at Great Inagua.",
            "missable": false
          },
          {
            "id": "portrait-10",
            "index": 10,
            "name": "Stede Bonnet",
            "location": "Captain Stede Bonnet side quest, Great Inagua 827,442",
            "method": "After Sequence 8 Memory 3, follow the quest to the stranded schooner on Mystery Island at 906,123 and finish its marked objectives.",
            "missable": false
          },
          {
            "id": "portrait-11",
            "index": 11,
            "name": "Robert Maynard",
            "location": "Port Royal below the central viewpoint, 602,134",
            "method": "After Sequence 11 Memory 3 and recruiting Lucy/Padre, advance the eight-part A World Without Gold chain to Reach Maynard's Treasure; collect it during or after the finale.",
            "missable": false
          }
        ]
      }
    },
    {
      "apiName": "ACObsidian_Ach_4",
      "displayName": "Dilettante",
      "description": "Fill all Art Collection and Equipment slots in the Great Inagua manor",
      "hidden": false,
      "globalPercent": 0.0,
      "flags": {
        "missable": false,
        "online": false,
        "grind": true,
        "glitched": false,
        "dlc": false
      },
      "difficulty": 5,
      "estTime": "10–15 hours alongside story",
      "estMinutes": 720,
      "stage": 5,
      "confidence": "verified",
      "summary": "Fill every @mechanic{Art Collection} and @mechanic{Equipment} slot in the @loc{Great Inagua manor}.",
      "guide": {
        "kind": "standard",
        "context": "Start this after Sequence 4 Memory 1. The long pole is 19 random art pieces from Brig piracy missions in Kenway's Fleet.",
        "steps": [
          {
            "id": "fleet",
            "text": "Keep five high-health Brigs in the fleet and run five piracy missions at once. Before accepting a completed mission report, save; accept it and inspect the newly rolled Brig missions, then reload until one shows the Art Piece reward icon before dispatching a Brig."
          },
          {
            "id": "art",
            "text": "Display all 11 portraits and fill the other art categories: 9 paintings, 7 table decorations, 2 large-table decorations, 3 furniture pieces and 27 shelf decorations. The first loot of each warehouse supplies paintings; stores, chests, treasures, local events and Brig piracy missions supply Art Pieces."
          },
          {
            "id": "equipment",
            "text": "Display 1 outfit, any 18 swords, any 12 pistols and all 20 ship models. Models come from story progress, quest rewards and defeating each ship/legendary type."
          },
          {
            "id": "check",
            "text": "Walk through every manor display room and interact with any empty slot; owning an item without placing it does not finish the requirement."
          }
        ]
      }
    },
    {
      "apiName": "ACObsidian_Ach_5",
      "displayName": "Governor",
      "description": "Restore all buildings in the Great Inagua village",
      "hidden": false,
      "globalPercent": 22.3,
      "flags": {
        "missable": false,
        "online": false,
        "grind": false,
        "glitched": false,
        "dlc": false
      },
      "difficulty": 2,
      "estTime": "30 min plus 23,100 Reales",
      "estMinutes": 30,
      "stage": 2,
      "confidence": "verified",
      "summary": "Restore the first level of all seven buildings in @loc{Great Inagua village}.",
      "guide": {
        "kind": "standard",
        "context": "The village opens in Sequence 4 Memory 1. The manor facade is cosmetic and not required.",
        "steps": [
          {
            "id": "funds",
            "text": "Save 23,100 Reales for the required restorations."
          },
          {
            "id": "restore",
            "text": "Buy level 1 of the General Store (500), Tavern (100), Harbourmaster (500), Brothel (6,000), Campfire (6,000), Treasure Dealer (5,000) and Fisherman's Wharf (5,000)."
          },
          {
            "id": "verify",
            "text": "The unlock fires as soon as all seven village building icons show their first restoration level."
          }
        ]
      }
    },
    {
      "apiName": "ACObsidian_Ach_6",
      "displayName": "Zero Waste",
      "description": "Restore a map from map pieces",
      "hidden": false,
      "globalPercent": 2.8,
      "flags": {
        "missable": false,
        "online": false,
        "grind": false,
        "glitched": false,
        "dlc": false
      },
      "difficulty": 3,
      "estTime": "1–3 hours",
      "estMinutes": 120,
      "stage": 2,
      "confidence": "verified",
      "summary": "Collect every piece of one @item{treasure map} and restore it.",
      "guide": {
        "kind": "standard",
        "context": "First restore the @loc{Great Inagua Treasure Dealer} at 817,448. Any complete map set works.",
        "steps": [
          {
            "id": "choose",
            "text": "For the straightforward Digested map, kill the @item{White Jaguar} around 825,439 twice for two pieces; it returns after roughly two hours of play."
          },
          {
            "id": "cargo",
            "text": "Gather 200 Rum by boarding ships around @loc{Gibara}."
          },
          {
            "id": "craft",
            "text": "Return to the Treasure Dealer and combine the two map pieces with the Rum to restore Digested and unlock the achievement."
          }
        ]
      }
    },
    {
      "apiName": "ACObsidian_Ach_7",
      "displayName": "Grandmaster",
      "description": "Win at each of the different tavern games",
      "hidden": false,
      "globalPercent": 1.7,
      "flags": {
        "missable": false,
        "online": false,
        "grind": false,
        "glitched": false,
        "dlc": false
      },
      "difficulty": 3,
      "estTime": "30 min",
      "estMinutes": 30,
      "stage": 2,
      "confidence": "verified",
      "summary": "Win one match of each of the three @mechanic{tavern games}.",
      "guide": {
        "kind": "standard",
        "context": "A one-star opponent is enough; you do not need to clear every table.",
        "steps": [
          {
            "id": "morris",
            "text": "Win Nine-Man Morris at @loc{Salt Key Bank} (467,605)."
          },
          {
            "id": "checkers",
            "text": "Win Checkers at @loc{Andreas Island} (543,697)."
          },
          {
            "id": "fanorona",
            "text": "Win Fanorona at @loc{Crooked Island} (777,520); the third distinct victory triggers the achievement."
          }
        ]
      }
    },
    {
      "apiName": "ACObsidian_Ach_8",
      "displayName": "Articles Of Agreement",
      "description": "Ensure the survival of all pirates in a street fight",
      "hidden": false,
      "globalPercent": 48.9,
      "flags": {
        "missable": false,
        "online": false,
        "grind": false,
        "glitched": false,
        "dlc": false
      },
      "difficulty": 2,
      "estTime": "5 min",
      "estMinutes": 5,
      "stage": 1,
      "confidence": "verified",
      "summary": "Finish a @mechanic{street fight} with every allied pirate still alive.",
      "guide": {
        "kind": "standard",
        "context": "Street fights appear as random chain icons in populated cities. Havana has frequent, low-risk spawns.",
        "steps": [
          {
            "id": "find",
            "text": "Roam @loc{Havana} until a chain-icon street fight appears, then enter the event before it expires."
          },
          {
            "id": "protect",
            "text": "Focus enemies attacking wounded allies and use smoke for crowd control; all pirates must survive until the final enemy falls."
          }
        ]
      }
    },
    {
      "apiName": "ACObsidian_Ach_9",
      "displayName": "Among Thieves",
      "description": "Unlock a smuggler's chest",
      "hidden": false,
      "globalPercent": 24.2,
      "flags": {
        "missable": false,
        "online": false,
        "grind": false,
        "glitched": false,
        "dlc": false
      },
      "difficulty": 2,
      "estTime": "10 min",
      "estMinutes": 10,
      "stage": 2,
      "confidence": "verified",
      "summary": "Steal the key and open the underwater @item{smuggler's chest} in @loc{Jiguey cave}.",
      "guide": {
        "kind": "standard",
        "context": "The cave entrance is at 535,511.",
        "steps": [
          {
            "id": "key",
            "text": "Enter Jiguey cave and kill the ordinary enemy standing beside the brute; loot the smuggler's key from him."
          },
          {
            "id": "chest",
            "text": "Dive into the cave pool, swim to the locked chest and use the key to open it."
          }
        ]
      }
    },
    {
      "apiName": "ACObsidian_Ach_10",
      "displayName": "Help A Brother Out",
      "description": "Complete a Templar Hunt sequence",
      "hidden": false,
      "globalPercent": 35.0,
      "flags": {
        "missable": false,
        "online": false,
        "grind": false,
        "glitched": false,
        "dlc": false
      },
      "difficulty": 3,
      "estTime": "1 hour",
      "estMinutes": 60,
      "stage": 2,
      "confidence": "verified",
      "summary": "Complete all four missions in any one @mechanic{Templar Hunt} sequence.",
      "guide": {
        "kind": "standard",
        "context": "Templar Hunts open after Sequence 4 Memory 1. Only one full chain is required.",
        "steps": [
          {
            "id": "pick",
            "text": "Choose Rhona, Antó, Upton or Opía and follow that contact's map markers."
          },
          {
            "id": "finish",
            "text": "Complete all four linked missions for the same contact; switching between chains does not count as one completed sequence."
          }
        ]
      }
    },
    {
      "apiName": "ACObsidian_Ach_11",
      "displayName": "Seven Deadly Seas",
      "description": "Find all treasure chests in underwater shipwrecks",
      "hidden": false,
      "globalPercent": 2.5,
      "flags": {
        "missable": false,
        "online": false,
        "grind": true,
        "glitched": false,
        "dlc": false
      },
      "difficulty": 4,
      "estTime": "4–5 hours",
      "estMinutes": 270,
      "stage": 3,
      "confidence": "verified",
      "summary": "Loot all 68 treasure chests across the seven @mechanic{underwater shipwrecks}.",
      "guide": {
        "kind": "standard",
        "context": "The diving bell and all seven wreck icons unlock after Sequence 6 Memory 1, Diving for Medicines. The total is 61 regular chests plus one secret chest at each wreck.",
        "steps": [
          {
            "id": "clear",
            "text": "At each shipwreck, use the diving bell and keep collecting until the location counter shows every chest complete."
          },
          {
            "id": "survive",
            "text": "Plan routes between air barrels, hiding spots and bell pockets; use the map pulse to catch chests tucked inside hulls or caves."
          },
          {
            "id": "verify",
            "text": "Review all seven wreck icons for complete chest counters. Opening the 68th chest unlocks the achievement."
          }
        ]
      }
    },
    {
      "apiName": "ACObsidian_Ach_12",
      "displayName": "Silence, Fool!",
      "description": "Kill a guard ringing a bell",
      "hidden": false,
      "globalPercent": 23.2,
      "flags": {
        "missable": false,
        "online": false,
        "grind": false,
        "glitched": false,
        "dlc": false
      },
      "difficulty": 2,
      "estTime": "5 min",
      "estMinutes": 5,
      "stage": 1,
      "confidence": "verified",
      "summary": "Kill a guard while he is actively ringing an @item{alarm bell}.",
      "guide": {
        "kind": "standard",
        "context": "A plantation warehouse is the most controlled setup; @loc{Matanzas} at 304,620 works well.",
        "steps": [
          {
            "id": "alert",
            "text": "Enter the restricted warehouse area and let the guards detect you."
          },
          {
            "id": "wait",
            "text": "Watch for the bell icon and let one guard reach the bell and begin the ringing animation."
          },
          {
            "id": "kill",
            "text": "Shoot or assassinate him before the animation ends. Killing him while merely running toward the bell does not count."
          }
        ]
      }
    },
    {
      "apiName": "ACObsidian_Ach_13",
      "displayName": "Matador",
      "description": "Dodge a total of three charge attacks by a Wild Pig",
      "hidden": false,
      "globalPercent": 5.4,
      "flags": {
        "missable": false,
        "online": false,
        "grind": false,
        "glitched": false,
        "dlc": false
      },
      "difficulty": 2,
      "estTime": "5 min",
      "estMinutes": 5,
      "stage": 1,
      "confidence": "verified",
      "summary": "Dodge three charge attacks from @item{Wild Pigs}.",
      "guide": {
        "kind": "standard",
        "context": "The same animal can provide all three dodges. @loc{Cape Bonavista} (152,588) has an easy Wild Pig spawn.",
        "steps": [
          {
            "id": "bait",
            "text": "Approach the pig and hold position until its charge warning turns red."
          },
          {
            "id": "dodge",
            "text": "Dodge sideways just before impact, then face it again and repeat twice more without killing it."
          }
        ]
      }
    },
    {
      "apiName": "ACObsidian_Ach_14",
      "displayName": "Perfect Predator",
      "description": "Get a perfect harpoon shot on a Great White Shark",
      "hidden": false,
      "globalPercent": 6.9,
      "flags": {
        "missable": false,
        "online": false,
        "grind": false,
        "glitched": false,
        "dlc": false
      },
      "difficulty": 3,
      "estTime": "10 min",
      "estMinutes": 10,
      "stage": 3,
      "confidence": "verified",
      "summary": "Land a perfect charged harpoon on a @item{Great White Shark}.",
      "guide": {
        "kind": "standard",
        "context": "Use the Great White Shark harpoon spot at @loc{Cruz} (490,303). Only the timing of one throw matters.",
        "steps": [
          {
            "id": "aim",
            "text": "Track the shark, hold the fire input to charge and keep the reticle centered."
          },
          {
            "id": "release",
            "text": "Release exactly as the reticle pulses/contracts to its smallest size; a perfect-hit cue and the achievement confirm the timing."
          }
        ]
      }
    },
    {
      "apiName": "ACObsidian_Ach_15",
      "displayName": "Double Tap",
      "description": "Parry two Ocelot attacks in rapid succession",
      "hidden": false,
      "globalPercent": 8.5,
      "flags": {
        "missable": false,
        "online": false,
        "grind": false,
        "glitched": false,
        "dlc": false
      },
      "difficulty": 3,
      "estTime": "5 min",
      "estMinutes": 5,
      "stage": 1,
      "confidence": "verified",
      "summary": "Parry two attacks from one @item{Ocelot} in rapid succession.",
      "guide": {
        "kind": "standard",
        "context": "Find an Ocelot at @loc{Abaco Island} (583,807). Do not damage it between parries.",
        "steps": [
          {
            "id": "first",
            "text": "Let the Ocelot attack and press parry on its warning to deflect the first leap."
          },
          {
            "id": "second",
            "text": "Immediately move close enough to provoke another attack and parry again before the rapid-success window expires."
          }
        ]
      }
    },
    {
      "apiName": "ACObsidian_Ach_16",
      "displayName": "Owned",
      "description": "Complete every activity in a single location",
      "hidden": false,
      "globalPercent": 53.3,
      "flags": {
        "missable": false,
        "online": false,
        "grind": false,
        "glitched": false,
        "dlc": false
      },
      "difficulty": 1,
      "estTime": "20 min",
      "estMinutes": 20,
      "stage": 1,
      "confidence": "verified",
      "summary": "Complete every activity and collectible in one @mechanic{location}.",
      "guide": {
        "kind": "standard",
        "context": "Choose a small island with few icons, or wait for the first shipwreck: fully looting a wreck also satisfies the requirement.",
        "steps": [
          {
            "id": "reveal",
            "text": "Synchronize the location's viewpoint, if present, to reveal its activity and collectible counters."
          },
          {
            "id": "clear",
            "text": "Finish every displayed icon and verify each counter is complete; the unlock occurs as the location reaches 100%."
          }
        ]
      }
    },
    {
      "apiName": "ACObsidian_Ach_17",
      "displayName": "The Hangman",
      "description": "Kill 10 enemies by hanging them with the rope dart",
      "hidden": false,
      "globalPercent": 3.7,
      "flags": {
        "missable": false,
        "online": false,
        "grind": true,
        "glitched": false,
        "dlc": false
      },
      "difficulty": 4,
      "estTime": "1–3 hours",
      "estMinutes": 120,
      "stage": 2,
      "confidence": "verified",
      "summary": "Perform 10 hanging kills with the @item{rope dart}.",
      "guide": {
        "kind": "standard",
        "context": "Rope darts unlock in Sequence 3. The kill must use the Hang prompt from a branch or overhead beam, not a normal rope-dart pull.",
        "steps": [
          {
            "id": "setup",
            "text": "Climb directly above an unaware guard at @loc{Tortuga} (848,350), @loc{Cat Island} (707,666) or the @loc{Kingston warehouse} (605,156)."
          },
          {
            "id": "hang",
            "text": "Aim the rope dart and use the on-screen Hang action, holding it until the guard dies."
          },
          {
            "id": "repeat",
            "text": "Repeat on 10 separate guards. Reloading does not instantly repopulate them; rotate locations or return after several hours of play."
          }
        ]
      }
    },
    {
      "apiName": "ACObsidian_Ach_18",
      "displayName": "Caught 'Em All",
      "description": "Catch at least five enemies within a single smoke bomb",
      "hidden": false,
      "globalPercent": 23.6,
      "flags": {
        "missable": false,
        "online": false,
        "grind": false,
        "glitched": false,
        "dlc": false
      },
      "difficulty": 2,
      "estTime": "5 min",
      "estMinutes": 5,
      "stage": 1,
      "confidence": "verified",
      "summary": "Catch at least five enemies inside one @item{smoke bomb} cloud.",
      "guide": {
        "kind": "standard",
        "context": "Smoke bombs unlock in Sequence 2 Memory 1. Ship boardings naturally cluster enough enemies.",
        "steps": [
          {
            "id": "group",
            "text": "During a boarding or city chase, let at least five hostile guards crowd around Edward."
          },
          {
            "id": "throw",
            "text": "Drop one smoke bomb in the middle of the group; all five must be visibly choking from that same cloud."
          }
        ]
      }
    },
    {
      "apiName": "ACObsidian_Ach_19",
      "displayName": "Gun-kata",
      "description": "Use pistols to kill four enemies in a row within five seconds",
      "hidden": false,
      "globalPercent": 17.7,
      "flags": {
        "missable": false,
        "online": false,
        "grind": false,
        "glitched": false,
        "dlc": false
      },
      "difficulty": 4,
      "estTime": "20 min",
      "estMinutes": 20,
      "stage": 2,
      "confidence": "verified",
      "summary": "Kill four enemies with pistols, in sequence, within five seconds.",
      "guide": {
        "kind": "standard",
        "context": "Craft holster level 4 first: level 3 needs two Rabbit pelts; level 4 needs four Bull Shark skins.",
        "steps": [
          {
            "id": "prepare",
            "text": "At @loc{Matanzas} (304,622), weaken four isolated guards without killing them, then use sleep darts so they stay still."
          },
          {
            "id": "lineup",
            "text": "Stand where all four are in range and confirm all four pistol chambers are loaded."
          },
          {
            "id": "fire",
            "text": "Shoot each sleeping guard once without pausing; all four deaths must land within the five-second window."
          }
        ]
      }
    },
    {
      "apiName": "ACObsidian_Ach_20",
      "displayName": "Backs To The Wall",
      "description": "Kill an enemy with a wall takedown",
      "hidden": false,
      "globalPercent": 77.8,
      "flags": {
        "missable": false,
        "online": false,
        "grind": false,
        "glitched": false,
        "dlc": false
      },
      "difficulty": 1,
      "estTime": "2 min",
      "estMinutes": 2,
      "stage": 1,
      "confidence": "verified",
      "summary": "Kill an enemy with a @mechanic{wall takedown}.",
      "guide": {
        "kind": "standard",
        "context": "Any ordinary guard beside a solid wall works.",
        "steps": [
          {
            "id": "kick",
            "text": "Fight near a wall and use Kick to drive the guard against it."
          },
          {
            "id": "finish",
            "text": "While the guard is pinned/stunned, use the displayed Takedown prompt before he steps away."
          }
        ]
      }
    },
    {
      "apiName": "ACObsidian_Ach_21",
      "displayName": "Let Me Explain",
      "description": "After a perfect parry, perform a total of four takedowns",
      "hidden": false,
      "globalPercent": 8.0,
      "flags": {
        "missable": false,
        "online": false,
        "grind": false,
        "glitched": false,
        "dlc": false
      },
      "difficulty": 4,
      "estTime": "10 min",
      "estMinutes": 10,
      "stage": 2,
      "confidence": "verified",
      "summary": "After one perfect parry, chain four @mechanic{takedowns}.",
      "guide": {
        "kind": "standard",
        "context": "Buy @item{Officer's Rapiers} from level 2 of the Great Inagua General Store; their combo allows four takedowns.",
        "steps": [
          {
            "id": "crowd",
            "text": "Start a fight with at least five guards, preferably during a ship boarding or plantation alarm."
          },
          {
            "id": "parry",
            "text": "Perfect-parry a blue-warning attack, then immediately activate Takedown on a nearby enemy."
          },
          {
            "id": "chain",
            "text": "Move the prompt from target to target and complete four takedowns before the combo expires."
          }
        ]
      }
    },
    {
      "apiName": "ACObsidian_Ach_22",
      "displayName": "Overdesign IV",
      "description": "Kick a berserk enemy caught in smoke off a ship",
      "hidden": false,
      "globalPercent": 0.8,
      "flags": {
        "missable": false,
        "online": false,
        "grind": false,
        "glitched": false,
        "dlc": false
      },
      "difficulty": 5,
      "estTime": "15 min",
      "estMinutes": 15,
      "stage": 2,
      "confidence": "verified",
      "summary": "Kick a berserk, smoke-stunned enemy off a ship.",
      "guide": {
        "kind": "standard",
        "context": "You need smoke bombs (Sequence 2 Memory 1), berserk darts (Sequence 4 Memory 4) and a Brig with a low rail.",
        "steps": [
          {
            "id": "board",
            "text": "Disable and board a Brig, then identify an enemy standing near a low section of railing."
          },
          {
            "id": "status",
            "text": "Hit that enemy with a berserk dart; once the purple berserk state is active, throw smoke so he is coughing inside the cloud."
          },
          {
            "id": "eject",
            "text": "Run at him front-on, kick him against a short rail and use Takedown while both status conditions remain active. Side takedowns often use the hidden blades; repeat if the animation does not knock him fully into the water."
          }
        ]
      }
    },
    {
      "apiName": "ACObsidian_Ach_23",
      "displayName": "Lively Havana",
      "description": "Get a tour of Havana (complete Sequence 2, Memory 1)",
      "hidden": false,
      "globalPercent": 92.6,
      "flags": {
        "missable": false,
        "online": false,
        "grind": false,
        "glitched": false,
        "dlc": false
      },
      "difficulty": 1,
      "estTime": "story",
      "estMinutes": 1,
      "stage": 1,
      "confidence": "verified",
      "summary": "Complete @loc{Sequence 2, Memory 1 — Lively Havana}.",
      "guide": {
        "kind": "standard",
        "context": "This is an automatic story achievement.",
        "steps": [
          {
            "id": "story",
            "text": "Follow Stede Bonnet through Havana and finish Sequence 2 Memory 1; it unlocks at the memory-complete screen."
          }
        ]
      }
    },
    {
      "apiName": "ACObsidian_Ach_24",
      "displayName": "A Poxy Bird",
      "description": "Become captain of the Jackdaw by completing Sequence 2, Memory 6.",
      "hidden": true,
      "globalPercent": 79.8,
      "flags": {
        "missable": false,
        "online": false,
        "grind": false,
        "glitched": false,
        "dlc": false
      },
      "difficulty": 1,
      "estTime": "story",
      "estMinutes": 1,
      "stage": 1,
      "confidence": "verified",
      "summary": "Complete @loc{Sequence 2, Memory 6 — The Treasure Fleet}.",
      "guide": {
        "kind": "standard",
        "context": "This hidden achievement is automatic story progress.",
        "steps": [
          {
            "id": "story",
            "text": "Finish The Treasure Fleet and take command of the Jackdaw; the achievement unlocks at the end of the memory."
          }
        ]
      }
    },
    {
      "apiName": "ACObsidian_Ach_25",
      "displayName": "Walls That Hold Back The Wind",
      "description": "Establish a new home by completing Sequence 4, Memory 1.",
      "hidden": true,
      "globalPercent": 55.1,
      "flags": {
        "missable": false,
        "online": false,
        "grind": false,
        "glitched": false,
        "dlc": false
      },
      "difficulty": 1,
      "estTime": "story",
      "estMinutes": 1,
      "stage": 1,
      "confidence": "verified",
      "summary": "Complete @loc{Sequence 4, Memory 1 — This Old Cove}.",
      "guide": {
        "kind": "standard",
        "context": "This hidden achievement is automatic and also opens Great Inagua's restoration systems.",
        "steps": [
          {
            "id": "story",
            "text": "Finish This Old Cove; Great Inagua becomes Edward's base and the achievement unlocks."
          }
        ]
      }
    },
    {
      "apiName": "ACObsidian_Ach_26",
      "displayName": "In A World Without Gold",
      "description": "Witness the end of a legend by completing Sequence 8, Memory 1.",
      "hidden": true,
      "globalPercent": 8.4,
      "flags": {
        "missable": false,
        "online": false,
        "grind": false,
        "glitched": false,
        "dlc": false
      },
      "difficulty": 1,
      "estTime": "story",
      "estMinutes": 1,
      "stage": 4,
      "confidence": "verified",
      "summary": "Complete @loc{Sequence 8, Memory 1 — Do Not Go Gently}.",
      "guide": {
        "kind": "standard",
        "context": "This hidden achievement is automatic story progress.",
        "steps": [
          {
            "id": "story",
            "text": "Finish Do Not Go Gently in Sequence 8; the unlock appears at the memory-complete screen."
          }
        ]
      }
    },
    {
      "apiName": "ACObsidian_Ach_27",
      "displayName": "Ever A Splinter",
      "description": "Stop the Templar plot by completing the main-story mission Ever a Splinter.",
      "hidden": true,
      "globalPercent": 2.4,
      "flags": {
        "missable": false,
        "online": false,
        "grind": false,
        "glitched": false,
        "dlc": false
      },
      "difficulty": 1,
      "estTime": "story",
      "estMinutes": 1,
      "stage": 4,
      "confidence": "verified",
      "summary": "Complete the main-story mission @loc{Ever a Splinter}.",
      "guide": {
        "kind": "standard",
        "context": "This hidden achievement is automatic near the end of Sequence 12. Current references disagree on the memory number, so track the mission title.",
        "steps": [
          {
            "id": "story",
            "text": "Continue the main story until Ever a Splinter and finish the mission; no optional objective is required."
          }
        ]
      }
    },
    {
      "apiName": "ACObsidian_Ach_28",
      "displayName": "All Hands On Deck",
      "description": "Recruit all Officers",
      "hidden": false,
      "globalPercent": 2.5,
      "flags": {
        "missable": false,
        "online": false,
        "grind": false,
        "glitched": false,
        "dlc": false
      },
      "difficulty": 3,
      "estTime": "3–4 hours",
      "estMinutes": 210,
      "stage": 4,
      "confidence": "verified",
      "summary": "Recruit all five @mechanic{Officers} for the Jackdaw.",
      "guide": {
        "kind": "collectible",
        "context": "Two officers are story recruits and three require quest chains. Tobias cannot join until Lucy and Padre have been recruited.",
        "collectibles": [
          {
            "id": "officer-1",
            "index": 1,
            "name": "Adéwalé",
            "location": "Sequence 3 Memory 1",
            "method": "Joins automatically through the story.",
            "missable": false
          },
          {
            "id": "officer-2",
            "index": 2,
            "name": "Lucy",
            "location": "Salt Key Bank, then Great Inagua",
            "method": "Complete A Proper Shipwright at 446,620, then The One With Gun at 818,445.",
            "missable": false
          },
          {
            "id": "officer-3",
            "index": 3,
            "name": "Padre",
            "location": "Caracol, then Cumberland",
            "method": "Complete A Second Chance at 446,620, then Loyalty Has Its Rewards at 648,348.",
            "missable": false
          },
          {
            "id": "officer-4",
            "index": 4,
            "name": "Anne",
            "location": "Sequence 12 Memory 1",
            "method": "Joins automatically at the start of the memory.",
            "missable": false
          },
          {
            "id": "officer-5",
            "index": 5,
            "name": "Tobias",
            "location": "A World Without Gold quest chain",
            "method": "After Sequence 11 Memory 3, finish That Bastard Maynard (818,446), Not Even a Real Captain (616,154), What the Devil (728,705) and It's a Start (825,444).",
            "missable": false
          }
        ]
      }
    },
    {
      "apiName": "ACObsidian_Ach_29",
      "displayName": "Hungover ",
      "description": "Drink until Edward passes out at the Nassau tavern.",
      "hidden": true,
      "globalPercent": 10.5,
      "flags": {
        "missable": false,
        "online": false,
        "grind": false,
        "glitched": false,
        "dlc": false
      },
      "difficulty": 1,
      "estTime": "5 min",
      "estMinutes": 5,
      "stage": 1,
      "confidence": "verified",
      "summary": "Buy enough drinks to black out at the @loc{Nassau tavern}.",
      "guide": {
        "kind": "standard",
        "context": "This hidden achievement is available once the Nassau tavern is accessible.",
        "steps": [
          {
            "id": "drink",
            "text": "Interact with the bottle on the tavern counter and keep buying drinks—normally at least five—without leaving."
          },
          {
            "id": "wake",
            "text": "Continue until Edward collapses and wakes in a haystack; the blackout triggers the achievement."
          }
        ]
      }
    },
    {
      "apiName": "ACObsidian_Ach_30",
      "displayName": "Collective Madness",
      "description": "Add one of each ship class to Kenway's fleet",
      "hidden": false,
      "globalPercent": 14.2,
      "flags": {
        "missable": false,
        "online": false,
        "grind": false,
        "glitched": false,
        "dlc": false
      },
      "difficulty": 2,
      "estTime": "30 min alongside story",
      "estMinutes": 30,
      "stage": 2,
      "confidence": "verified",
      "summary": "Send a Schooner, Brig, Frigate and Man-o-War to @mechanic{Kenway's Fleet}.",
      "guide": {
        "kind": "standard",
        "context": "The fleet unlocks in Sequence 4. The four ship classes do not need to remain in the fleet simultaneously.",
        "steps": [
          {
            "id": "board",
            "text": "Board one ship of each required class instead of sinking it."
          },
          {
            "id": "send",
            "text": "At the boarding resolution screen, choose Send to Kenway's Fleet for each class; the fourth distinct class completes the set."
          }
        ]
      }
    },
    {
      "apiName": "ACObsidian_Ach_31",
      "displayName": "Strike The Colors",
      "description": "Board a Lead Convoy ship",
      "hidden": false,
      "globalPercent": 37.4,
      "flags": {
        "missable": false,
        "online": false,
        "grind": false,
        "glitched": false,
        "dlc": false
      },
      "difficulty": 3,
      "estTime": "15 min",
      "estMinutes": 15,
      "stage": 2,
      "confidence": "verified",
      "summary": "Board the lead ship in a timed @mechanic{Naval Convoy} event.",
      "guide": {
        "kind": "standard",
        "context": "Look for a white timed convoy icon whose map label includes Lead Convoy Ship.",
        "steps": [
          {
            "id": "intercept",
            "text": "Sail to the convoy before its timer expires and identify the marked lead merchant vessel."
          },
          {
            "id": "board",
            "text": "Reduce the lead ship to boarding health, pull alongside, board it and complete the boarding objective; sinking it does not count."
          }
        ]
      }
    },
    {
      "apiName": "ACObsidian_Ach_32",
      "displayName": "Unsinkable",
      "description": "Survive a rogue wave taken from the side",
      "hidden": false,
      "globalPercent": 8.4,
      "flags": {
        "missable": false,
        "online": false,
        "grind": false,
        "glitched": false,
        "dlc": false
      },
      "difficulty": 2,
      "estTime": "5 min in Sequence 2 Memory 6",
      "estMinutes": 5,
      "stage": 1,
      "confidence": "verified",
      "summary": "Survive a @mechanic{rogue wave} that strikes the Jackdaw from the side.",
      "guide": {
        "kind": "standard",
        "context": "Sequence 2 Memory 6 guarantees a storm; random rogue waves also occur later in free roam.",
        "steps": [
          {
            "id": "broadside",
            "text": "When the wave warning appears, turn so the wave hits the Jackdaw's broadside rather than the bow."
          },
          {
            "id": "brace",
            "text": "Hold Brace before impact and survive the damage. The achievement unlocks once the ship clears the wave."
          }
        ]
      }
    },
    {
      "apiName": "ACObsidian_Ach_33",
      "displayName": "Yo Ho…",
      "description": "Learn a new shanty",
      "hidden": false,
      "globalPercent": 81.3,
      "flags": {
        "missable": false,
        "online": false,
        "grind": false,
        "glitched": false,
        "dlc": false
      },
      "difficulty": 1,
      "estTime": "2 min",
      "estMinutes": 2,
      "stage": 1,
      "confidence": "verified",
      "summary": "Learn any new @item{sea shanty}.",
      "guide": {
        "kind": "standard",
        "context": "Chase any music-note collectible through a town; one is also learned through Sequence 8 Memory 1.",
        "steps": [
          {
            "id": "chase",
            "text": "Touch a shanty sheet to begin its parkour route and follow it until Edward catches the page."
          },
          {
            "id": "unlock",
            "text": "The first collected or story-awarded shanty triggers the achievement."
          }
        ]
      }
    },
    {
      "apiName": "ACObsidian_Ach_34",
      "displayName": "Return The Favor",
      "description": "Dash ram a ramming Brig",
      "hidden": false,
      "globalPercent": 14.1,
      "flags": {
        "missable": false,
        "online": false,
        "grind": false,
        "glitched": false,
        "dlc": false
      },
      "difficulty": 3,
      "estTime": "10 min",
      "estMinutes": 10,
      "stage": 2,
      "confidence": "verified",
      "summary": "Use @mechanic{Ram-Dash} against a Brig while it is attempting to ram you.",
      "guide": {
        "kind": "standard",
        "context": "Recruit Padre through his two quests, then buy the first Jackdaw ram upgrade to unlock Ram-Dash.",
        "steps": [
          {
            "id": "bait",
            "text": "Engage a Brig and keep the bow facing it until it sounds its horn and starts a ramming run."
          },
          {
            "id": "counter",
            "text": "Activate Ram-Dash straight into the Brig before its charge ends; an ordinary-speed collision does not count."
          }
        ]
      }
    },
    {
      "apiName": "ACObsidian_Ach_35",
      "displayName": "Hunter Hunted",
      "description": "Defeat a Pirate Hunter while at maximum Wanted Level",
      "hidden": false,
      "globalPercent": 6.0,
      "flags": {
        "missable": false,
        "online": false,
        "grind": false,
        "glitched": false,
        "dlc": false
      },
      "difficulty": 4,
      "estTime": "20 min",
      "estMinutes": 20,
      "stage": 2,
      "confidence": "verified",
      "summary": "Defeat a @mechanic{Pirate Hunter} while at wanted level 4.",
      "guide": {
        "kind": "standard",
        "context": "Build wanted level by sinking and boarding ships without lowering notoriety.",
        "steps": [
          {
            "id": "wanted",
            "text": "Continue attacking vessels until all four wanted-level pips are lit."
          },
          {
            "id": "hunter",
            "text": "Wait for the Pirate Hunter to spawn, then sink or board it while the four-pip wanted level is still active."
          }
        ]
      }
    },
    {
      "apiName": "ACObsidian_Ach_36",
      "displayName": "Devil of the Caribbean",
      "description": "Defeat all legendary ships",
      "hidden": false,
      "globalPercent": 1.3,
      "flags": {
        "missable": false,
        "online": false,
        "grind": true,
        "glitched": false,
        "dlc": false
      },
      "difficulty": 6,
      "estTime": "2–3 hours after upgrading",
      "estMinutes": 150,
      "stage": 4,
      "prerequisites": [
        "ACObsidian_Ach_42"
      ],
      "sortReason": "Fully upgrade the Jackdaw before attempting the five legendary ships.",
      "confidence": "verified",
      "summary": "Defeat all five @mechanic{legendary ships}.",
      "guide": {
        "kind": "collectible",
        "context": "Fully upgrade the Jackdaw, recruit all officers and lower combat difficulty before starting. The paired encounter counts as two ships.",
        "collectibles": [
          {
            "id": "legend-1",
            "index": 1,
            "name": "El Impoluto",
            "location": "117,841",
            "method": "Keep range from its lethal ram, use brace during charges and punish after it passes.",
            "missable": false
          },
          {
            "id": "legend-2",
            "index": 2,
            "name": "La Dama Negra",
            "location": "240,72",
            "method": "Stay mobile, brace through mortar fire and attack its vulnerable stern/sides.",
            "missable": false
          },
          {
            "id": "legend-3",
            "index": 3,
            "name": "HMS Prince",
            "location": "854,55",
            "method": "Fight outside its strongest broadside angle and use mortars/fire barrels during turns.",
            "missable": false
          },
          {
            "id": "legend-4",
            "index": 4,
            "name": "HMS Fearless",
            "location": "811,858",
            "method": "In the paired battle, damage both ships evenly so the survivor does not spend long in its enraged state.",
            "missable": false
          },
          {
            "id": "legend-5",
            "index": 5,
            "name": "Royal Sovereign",
            "location": "811,858",
            "method": "Finish the second ship immediately after the first; defeating both completes the last legendary encounter.",
            "missable": false
          }
        ]
      }
    },
    {
      "apiName": "ACObsidian_Ach_37",
      "displayName": "Old Ironsides",
      "description": "Perform 3 perfect braces",
      "hidden": false,
      "globalPercent": 31.6,
      "flags": {
        "missable": false,
        "online": false,
        "grind": false,
        "glitched": false,
        "dlc": false
      },
      "difficulty": 3,
      "estTime": "10 min",
      "estMinutes": 10,
      "stage": 2,
      "confidence": "verified",
      "summary": "Perform three @mechanic{perfect braces} aboard the Jackdaw.",
      "guide": {
        "kind": "standard",
        "context": "Recruit Lucy through A Proper Shipwright and The One With Gun to enable the perfect-brace mechanic.",
        "steps": [
          {
            "id": "timing",
            "text": "Fight a ship with readable cannon volleys and wait for an incoming-attack warning."
          },
          {
            "id": "brace",
            "text": "Press and hold Brace just before the projectiles hit—not as soon as the warning appears—to earn the perfect-brace cue."
          },
          {
            "id": "repeat",
            "text": "Land three perfect timings across any naval fights; they do not need to be in one encounter."
          }
        ]
      }
    },
    {
      "apiName": "ACObsidian_Ach_38",
      "displayName": "Not So Little Friend",
      "description": "Unlock the secondary firing mode on a Jackdaw weapon",
      "hidden": false,
      "globalPercent": 61.7,
      "flags": {
        "missable": false,
        "online": false,
        "grind": false,
        "glitched": false,
        "dlc": false
      },
      "difficulty": 1,
      "estTime": "story",
      "estMinutes": 1,
      "stage": 1,
      "confidence": "verified",
      "summary": "Unlock @item{burning shot}, the secondary mode for the Jackdaw's cannons.",
      "guide": {
        "kind": "standard",
        "context": "This is an automatic story unlock.",
        "steps": [
          {
            "id": "story",
            "text": "Complete Sequence 3 Memory 6, Proper Defenses; burning shot becomes available after the mission and triggers the achievement."
          }
        ]
      }
    },
    {
      "apiName": "ACObsidian_Ach_39",
      "displayName": "Dressing Overall",
      "description": "Equip new cosmetics in each of the Jackdaw's vanity slots",
      "hidden": false,
      "globalPercent": 31.3,
      "flags": {
        "missable": false,
        "online": false,
        "grind": false,
        "glitched": false,
        "dlc": false
      },
      "difficulty": 2,
      "estTime": "5 min",
      "estMinutes": 5,
      "stage": 2,
      "confidence": "verified",
      "summary": "Equip a new cosmetic in all five @mechanic{Jackdaw vanity slots}.",
      "guide": {
        "kind": "standard",
        "context": "Restore the Great Inagua Harbourmaster at 818,440 for 500 Reales, then open Appearance.",
        "steps": [
          {
            "id": "equip",
            "text": "Change Sails, Figurehead, Hull, Wheel and Crew to an option other than the currently equipped one."
          },
          {
            "id": "verify",
            "text": "Back out after all five slots show a changed selection; price and rarity do not matter."
          }
        ]
      }
    },
    {
      "apiName": "ACObsidian_Ach_40",
      "displayName": "Smooth Operator",
      "description": "Craft an item",
      "hidden": false,
      "globalPercent": 78.1,
      "flags": {
        "missable": false,
        "online": false,
        "grind": false,
        "glitched": false,
        "dlc": false
      },
      "difficulty": 1,
      "estTime": "story tutorial",
      "estMinutes": 1,
      "stage": 1,
      "confidence": "verified",
      "summary": "Craft any @item{item}.",
      "guide": {
        "kind": "standard",
        "context": "Sequence 3 Memory 1 includes a mandatory crafting tutorial.",
        "steps": [
          {
            "id": "craft",
            "text": "Follow the tutorial to use gathered materials at the anvil; the first completed recipe unlocks the achievement."
          }
        ]
      }
    },
    {
      "apiName": "ACObsidian_Ach_41",
      "displayName": "Business And Pleasure",
      "description": "Spend 50,000 Reales",
      "hidden": false,
      "globalPercent": 38.8,
      "flags": {
        "missable": false,
        "online": false,
        "grind": false,
        "glitched": false,
        "dlc": false
      },
      "difficulty": 2,
      "estTime": "automatic during upgrades",
      "estMinutes": 1,
      "stage": 2,
      "confidence": "verified",
      "summary": "Spend a cumulative 50,000 @item{Reales}.",
      "guide": {
        "kind": "standard",
        "context": "All purchases count, so normal Great Inagua restorations and Jackdaw upgrades will exceed the requirement.",
        "steps": [
          {
            "id": "spend",
            "text": "Prioritize required buildings, equipment and ship upgrades rather than buying disposable items solely for the counter."
          },
          {
            "id": "unlock",
            "text": "The achievement triggers when lifetime spending passes 50,000; money need not be spent in one transaction."
          }
        ]
      }
    },
    {
      "apiName": "ACObsidian_Ach_42",
      "displayName": "Ship This",
      "description": "Fully upgrade the Jackdaw",
      "hidden": false,
      "globalPercent": 1.8,
      "flags": {
        "missable": false,
        "online": false,
        "grind": true,
        "glitched": false,
        "dlc": false
      },
      "difficulty": 5,
      "estTime": "8–12 hours of resources/plans",
      "estMinutes": 600,
      "stage": 4,
      "confidence": "verified",
      "summary": "Buy every upgrade for the @mechanic{Jackdaw}.",
      "guide": {
        "kind": "standard",
        "context": "With the diving bell obtained free in Sequence 6 Memory 1, fully upgrading the Harbourmaster and Jackdaw costs 309,800 Reales, 4,755 metal, 2,750 wood and 550 cloth.",
        "steps": [
          {
            "id": "wreck-plans",
            "text": "Loot six shipwreck plans: Hull Armor at San Ignacio (348,744), Mortars at Antocha (600,636), Ram at La Concepción (150,271), Swivel Guns at Devil's Eye Caverns (456,332), Broadside Cannon Number at The Blue Hole (440,145), and Round Shot Strength at Kabah Ruins (738,120)."
          },
          {
            "id": "map-plans",
            "text": "Dig six treasure-map plans: Ambergris Key→Misteriosa (28,160→271,178), Santanillas→San Juan (191,218→455,462), Cayman Sound→Petite Caverne (298,311→863,235), Tortuga→Matanzas (851,352→312,617), Mariguana→Andreas Island (847,514→544,693), and Petite Caverne→Tulum (862,237→40,372)."
          },
          {
            "id": "resources",
            "text": "Board ships in harder regions, loot Captain's Lockboxes and capture forts to build the required cargo. Sell surplus Rum/Sugar but reserve metal, wood and cloth for upgrades."
          },
          {
            "id": "buy",
            "text": "Fully upgrade the Great Inagua Harbourmaster, then purchase every level in weapons, armor, storage and utility before starting the legendary ships."
          }
        ]
      }
    },
    {
      "apiName": "ACObsidian_Ach_43",
      "displayName": "Glutton for Nourishment",
      "description": "Consume 20 food items",
      "hidden": false,
      "globalPercent": 26.7,
      "flags": {
        "missable": false,
        "online": false,
        "grind": false,
        "glitched": false,
        "dlc": false
      },
      "difficulty": 2,
      "estTime": "20 min",
      "estMinutes": 20,
      "stage": 1,
      "confidence": "verified",
      "summary": "Consume 20 @item{food pickups} while injured.",
      "guide": {
        "kind": "standard",
        "context": "Berry bushes and soup bowls count; health flasks do not. Food can only be consumed when Edward has missing health.",
        "steps": [
          {
            "id": "hurt",
            "text": "Let a weak enemy damage Edward, escape combat, then eat a berry or soup pickup in the environment."
          },
          {
            "id": "farm",
            "text": "Repeat at storehouses and settlements as food respawns until the cumulative 20th pickup is consumed."
          }
        ]
      }
    },
    {
      "apiName": "ACObsidian_Ach_44",
      "displayName": "Friend To All",
      "description": "Interact with all seven friendly animals",
      "hidden": false,
      "globalPercent": 1.1,
      "flags": {
        "missable": false,
        "online": false,
        "grind": false,
        "glitched": false,
        "dlc": false
      },
      "difficulty": 3,
      "estTime": "1 hour",
      "estMinutes": 60,
      "stage": 3,
      "confidence": "verified",
      "summary": "Interact with all eight friendly animals—the current build requires one more than the Steam text says.",
      "guide": {
        "kind": "collectible",
        "context": "If an animal fails to appear, fast-travel away, advance to morning and return. The interaction prompt, not merely seeing the animal, records it.",
        "collectibles": [
          {
            "id": "animal-1",
            "index": 1,
            "name": "Monkey",
            "location": "Great Inagua manor or Jackdaw cabin",
            "method": "Complete Havana's Monkey Business Local Event, equip the monkey in the pet slot, then pet it.",
            "missable": false
          },
          {
            "id": "animal-2",
            "index": 2,
            "name": "Turtle",
            "location": "Abaco Island beach, 584,807",
            "method": "Approach slowly and use the interaction prompt.",
            "missable": false
          },
          {
            "id": "animal-3",
            "index": 3,
            "name": "Dog",
            "location": "Kingston docks, 617,167",
            "method": "Pet the dog near the dock area.",
            "missable": false
          },
          {
            "id": "animal-4",
            "index": 4,
            "name": "Pig",
            "location": "Kingston, fenced area by the General Store",
            "method": "Enter the pen and interact with the pig.",
            "missable": false
          },
          {
            "id": "animal-5",
            "index": 5,
            "name": "Chicken",
            "location": "Kingston, around town or near the pig pen",
            "method": "Use the prompt on any friendly chicken.",
            "missable": false
          },
          {
            "id": "animal-6",
            "index": 6,
            "name": "Cow",
            "location": "Kingston, east pen between the Monkey and Harbourmaster icons",
            "method": "Enter the fenced field and interact with the cow.",
            "missable": false
          },
          {
            "id": "animal-7",
            "index": 7,
            "name": "Cat",
            "location": "Kingston market, north of the central viewpoint",
            "method": "Pet the cat in the market square.",
            "missable": false
          },
          {
            "id": "animal-8",
            "index": 8,
            "name": "Parrot",
            "location": "Havana market cage, 211,586",
            "method": "Interact through the cage; alternatively use the parrot at a fully upgraded Great Inagua General Store.",
            "missable": false
          }
        ]
      }
    },
    {
      "apiName": "ACObsidian_Ach_45",
      "displayName": "Blow The Man Down",
      "description": "Shoot down all the hanging bodies in Long Bay",
      "hidden": false,
      "globalPercent": 0.3,
      "flags": {
        "missable": false,
        "online": false,
        "grind": false,
        "glitched": false,
        "dlc": false
      },
      "difficulty": 2,
      "estTime": "10 min",
      "estMinutes": 10,
      "stage": 4,
      "confidence": "verified",
      "summary": "Shoot down all three hanging bodies in @loc{Long Bay}.",
      "guide": {
        "kind": "collectible",
        "context": "Long Bay at 498,226 opens after Sequence 10 Memory 3. Shoot each corpse in the head from close range; the aiming cursor turns red when the shot is aligned correctly.",
        "collectibles": [
          {
            "id": "body-1",
            "index": 1,
            "name": "Viewpoint body",
            "location": "Top of Long Bay's northern viewpoint",
            "method": "Climb to the top platform, aim at the head until the cursor is red, and shoot until the body falls.",
            "missable": false
          },
          {
            "id": "body-2",
            "index": 2,
            "name": "Beach-path body 1",
            "location": "Roots above the start of the right-hand path near the beach",
            "method": "Jump from the viewpoint toward the beach, enter the right path back toward the ship, look up and headshot the first corpse.",
            "missable": false
          },
          {
            "id": "body-3",
            "index": 3,
            "name": "Beach-path body 2",
            "location": "Beside body 2 above the same roots",
            "method": "The last corpse hangs very close to body 2; headshot it from beneath the roots and confirm all three bodies have fallen.",
            "missable": false
          }
        ]
      }
    },
    {
      "apiName": "ACObsidian_Ach_46",
      "displayName": "Davy Jones' Locker",
      "description": "Discover the broken diving bell at the bottom of Black Trench.",
      "hidden": true,
      "globalPercent": 0.8,
      "flags": {
        "missable": false,
        "online": false,
        "grind": false,
        "glitched": false,
        "dlc": false
      },
      "difficulty": 2,
      "estTime": "10 min",
      "estMinutes": 10,
      "stage": 3,
      "confidence": "verified",
      "summary": "Reach the broken @item{diving bell} deep below @loc{Black Trench}.",
      "guide": {
        "kind": "standard",
        "context": "The Black Trench wreck at 184,425 is available after Sequence 6 Memory 1.",
        "steps": [
          {
            "id": "route",
            "text": "Descend from your bell, swim forward-right to the large wreck and use the nearby air barrel."
          },
          {
            "id": "trench",
            "text": "Dive straight down into the deep trench until the broken diving bell comes into view."
          },
          {
            "id": "trigger",
            "text": "Swim around the broken bell and its base; if it does not unlock immediately, circle it once at close range."
          }
        ]
      }
    },
    {
      "apiName": "ACObsidian_Ach_47",
      "displayName": "Cartographer",
      "description": "Visit every location in the game",
      "hidden": false,
      "globalPercent": 0.9,
      "flags": {
        "missable": false,
        "online": false,
        "grind": true,
        "glitched": false,
        "dlc": false
      },
      "difficulty": 4,
      "estTime": "5–8 hours cleanup",
      "estMinutes": 390,
      "stage": 3,
      "confidence": "verified",
      "summary": "Visit all 57 named @mechanic{locations} in the Caribbean.",
      "guide": {
        "kind": "standard",
        "context": "Story destinations count automatically, but several sea locations require deliberately crossing their discovery boundary.",
        "steps": [
          {
            "id": "map",
            "text": "Sail through every remaining white question mark and named island/settlement until it becomes revealed on the map."
          },
          {
            "id": "forts",
            "text": "Approach each fort closely enough to reveal its defenses; capturing the fort is not required for this achievement."
          },
          {
            "id": "wrecks",
            "text": "Enter all seven shipwreck dive zones rather than only sailing over their icons."
          },
          {
            "id": "audit",
            "text": "Compare region counters and map filters for a total of 57; revisit any pale/unresolved icon until its location banner appears."
          }
        ]
      }
    },
    {
      "apiName": "ACObsidian_Ach_48",
      "displayName": "Edward Catway",
      "description": "Break 50 potted plants",
      "hidden": false,
      "globalPercent": 0.9,
      "flags": {
        "missable": false,
        "online": false,
        "grind": true,
        "glitched": false,
        "dlc": false
      },
      "difficulty": 2,
      "estTime": "20 min",
      "estMinutes": 20,
      "stage": 1,
      "confidence": "verified",
      "summary": "Break 50 distinct @item{potted plants}.",
      "guide": {
        "kind": "standard",
        "context": "Havana's streets, courtyards and balconies contain many pots. Respawned copies of a pot already broken do not advance the counter.",
        "steps": [
          {
            "id": "sweep",
            "text": "Walk a systematic loop through @loc{Havana}, meleeing every flowerpot on the ground, walls and accessible balconies."
          },
          {
            "id": "expand",
            "text": "Move to new districts or cities rather than farming a respawn route; the 50th unique pot triggers the achievement."
          }
        ]
      }
    },
    {
      "apiName": "ACObsidian_Ach_49",
      "displayName": "Ed the Diver",
      "description": "Swim a total of 1000m underwater, excluding underwater shipwrecks",
      "hidden": false,
      "globalPercent": 15.9,
      "flags": {
        "missable": false,
        "online": false,
        "grind": false,
        "glitched": false,
        "dlc": false
      },
      "difficulty": 2,
      "estTime": "20 min",
      "estMinutes": 20,
      "stage": 1,
      "confidence": "verified",
      "summary": "Swim 1,000 cumulative metres underwater outside shipwreck zones.",
      "guide": {
        "kind": "standard",
        "context": "Distance inside the seven diving-bell shipwreck areas is excluded, but ordinary sea, beach and cave swimming counts.",
        "steps": [
          {
            "id": "swim",
            "text": "At any calm coast, dive and swim long laps just below the surface so you can refill breath quickly."
          },
          {
            "id": "repeat",
            "text": "Continue across normal exploration sessions; the counter is cumulative and unlocks as soon as 1,000 valid metres are reached."
          }
        ]
      }
    }
  ],
  "completionOrder": [
    "ACObsidian_Ach_23",
    "ACObsidian_Ach_33",
    "ACObsidian_Ach_24",
    "ACObsidian_Ach_40",
    "ACObsidian_Ach_20",
    "ACObsidian_Ach_38",
    "ACObsidian_Ach_25",
    "ACObsidian_Ach_16",
    "ACObsidian_Ach_29",
    "ACObsidian_Ach_8",
    "ACObsidian_Ach_18",
    "ACObsidian_Ach_12",
    "ACObsidian_Ach_43",
    "ACObsidian_Ach_32",
    "ACObsidian_Ach_13",
    "ACObsidian_Ach_49",
    "ACObsidian_Ach_15",
    "ACObsidian_Ach_48",
    "ACObsidian_Ach_41",
    "ACObsidian_Ach_39",
    "ACObsidian_Ach_9",
    "ACObsidian_Ach_5",
    "ACObsidian_Ach_30",
    "ACObsidian_Ach_31",
    "ACObsidian_Ach_37",
    "ACObsidian_Ach_34",
    "ACObsidian_Ach_10",
    "ACObsidian_Ach_7",
    "ACObsidian_Ach_19",
    "ACObsidian_Ach_3",
    "ACObsidian_Ach_21",
    "ACObsidian_Ach_35",
    "ACObsidian_Ach_6",
    "ACObsidian_Ach_22",
    "ACObsidian_Ach_17",
    "ACObsidian_Ach_46",
    "ACObsidian_Ach_14",
    "ACObsidian_Ach_44",
    "ACObsidian_Ach_2",
    "ACObsidian_Ach_11",
    "ACObsidian_Ach_47",
    "ACObsidian_Ach_26",
    "ACObsidian_Ach_27",
    "ACObsidian_Ach_45",
    "ACObsidian_Ach_28",
    "ACObsidian_Ach_42",
    "ACObsidian_Ach_36",
    "ACObsidian_Ach_1",
    "ACObsidian_Ach_4"
  ]
}
